pack/__inti__.py
testingggggg-0.0.1.dist-info/METADATA
testingggggg-0.0.1.dist-info/WHEEL
testingggggg-0.0.1.dist-info/top_level.txt
testingggggg-0.0.1.dist-info/RECORD
