Metadata-Version: 2.1
Name: testingggggg
Version: 0.0.1
Summary: test
Home-page: UNKNOWN
Author: dex
License: UNKNOWN
Platform: UNKNOWN
Provides-Extra: extratesting
Requires-Dist: flask ; extra == 'extratesting'
